toshiba_ac/__init__.py
toshiba_ac/amqp_api.py
toshiba_ac/device.py
toshiba_ac/device_manager.py
toshiba_ac/fcu_state.py
toshiba_ac/http_api.py
toshiba_ac/utils.py
toshiba_ac-0.1.12.dist-info/LICENSE.txt
toshiba_ac-0.1.12.dist-info/METADATA
toshiba_ac-0.1.12.dist-info/WHEEL
toshiba_ac-0.1.12.dist-info/top_level.txt
toshiba_ac-0.1.12.dist-info/RECORD
